setup.py
cloudimage/__init__.py
cloudimage/cli.py
cloudimage/picture.py
cloudimagebeta.egg-info/PKG-INFO
cloudimagebeta.egg-info/SOURCES.txt
cloudimagebeta.egg-info/dependency_links.txt
cloudimagebeta.egg-info/top_level.txt