Metadata-Version: 1.0
Name: cloudimagebeta
Version: 0.1
Summary: Image processing with commandline UI
Home-page: UNKNOWN
Author: Maciej.Kuzma
Author-email: maciej.kuzma@outlook.com
License: UNKNOWN
Platform: UNKNOWN
